buf/__init__.py
buf/error_messages.py
buf/libraries.py
buf/main.py
buf/unit.py
buf/user_input.py
buf/commands/__init__.py
buf/commands/chemical.py
buf/commands/help.py
buf/commands/make.py
buf/commands/recipe.py
buf-1.0.0.dist-info/METADATA
buf-1.0.0.dist-info/RECORD
buf-1.0.0.dist-info/WHEEL
buf-1.0.0.dist-info/entry_points.txt
buf-1.0.0.dist-info/top_level.txt
