Metadata-Version: 2.1
Name: buf
Version: 1.0.0
Summary: For easily making chemical buffers and solutions
Home-page: https://buf.readthedocs.io/en/latest/index.html
Author: Jordan Juravsky
Author-email: jordan@mindcharger.com
License: UNKNOWN
Keywords: buf chemistry buffer solution salt
Platform: UNKNOWN
Classifier: Programming Language :: Python :: 3.6
Classifier: Programming Language :: Python :: 3.7
Classifier: License :: OSI Approved :: MIT License
Classifier: Operating System :: OS Independent
Requires-Python: >=3.6
Requires-Dist: docopt (==0.6.2)
Requires-Dist: tabulate (==0.8.2)
